[
    {
      "question": "L'action et la réaction sont deux forces égales mais opposées qui agissent toujours sur un même et seul objet.",
      "options": ["Vrai", "Faux"],
      "correctAnswer": "Vrai",
      "points": 1
    },
    {
      "question": "Dans une lutte entre deux personnes, sûrement le plus fort exercera une force plus grande que le moins fort et l'emportera.",
      "options": ["Vrai", "Faux"],
      "correctAnswer": "Faux",
      "points": 1
    },
    {
      "question": "L’action agit sur l’objet poussé ou tiré tandis que la réaction agit sur le pousseur ou le tireur.",
      "options": ["Vrai", "Faux"],
      "correctAnswer": "Faux",
      "points": 1
    },
    {
      "question": "L’action et la réaction ne s’annulent pas.",
      "options": ["Vrai", "Faux"],
      "correctAnswer": "Faux",
      "points": 1
    }
  ]
  